{".class": "MypyFile", "_fullname": "maggma.stores.advanced_stores", "is_partial_stub_package": false, "is_stub": false, "names": {".class": "SymbolTable", "AliasingStore": {".class": "SymbolTableNode", "kind": "Gdef", "node": {".class": "TypeInfo", "_promote": null, "abstract_attributes": [], "bases": ["maggma.core.store.Store"], "declared_metaclass": null, "defn": {".class": "ClassDef", "fullname": "maggma.stores.advanced_stores.AliasingStore", "name": "AliasingStore", "type_vars": []}, "flags": ["fallback_to_any"], "fullname": "maggma.stores.advanced_stores.AliasingStore", "metaclass_type": "abc.ABCMeta", "metadata": {}, "module_name": "maggma.stores.advanced_stores", "mro": ["maggma.stores.advanced_stores.AliasingStore", "maggma.core.store.Store", "builtins.object"], "names": {".class": "SymbolTable", "__eq__": {".class": "SymbolTableNode", "kind": "Mdef", "node": {".class": "FuncDef", "arg_kinds": [0, 0], "arg_names": ["self", "other"], "flags": [], "fullname": "maggma.stores.advanced_stores.AliasingStore.__eq__", "name": "__eq__", "type": {".class": "CallableType", "arg_kinds": [0, 0], "arg_names": [null, null], "arg_types": ["maggma.stores.advanced_stores.AliasingStore", "builtins.object"], "bound_args": [], "def_extras": {"first_arg": "self"}, "fallback": "builtins.function", "implicit": false, "is_ellipsis_args": false, "name": "__eq__ of AliasingStore", "ret_type": "builtins.bool", "variables": []}}}, "__init__": {".class": "SymbolTableNode", "kind": "Mdef", "node": {".class": "FuncDef", "arg_kinds": [0, 0, 0, 4], "arg_names": ["self", "store", "aliases", "kwargs"], "flags": [], "fullname": "maggma.stores.advanced_stores.AliasingStore.__init__", "name": "__init__", "type": {".class": "CallableType", "arg_kinds": [0, 0, 0, 4], "arg_names": ["self", "store", "aliases", "kwargs"], "arg_types": ["maggma.stores.advanced_stores.AliasingStore", "maggma.core.store.Store", {".class": "Instance", "args": [{".class": "AnyType", "missing_import_name": null, "source_any": null, "type_of_any": 4}, {".class": "AnyType", "missing_import_name": null, "source_any": null, "type_of_any": 4}], "type_ref": "builtins.dict"}, {".class": "AnyType", "missing_import_name": null, "source_any": null, "type_of_any": 1}], "bound_args": [], "def_extras": {"first_arg": "self"}, "fallback": "builtins.function", "implicit": false, "is_ellipsis_args": false, "name": "__init__ of AliasingStore", "ret_type": {".class": "NoneType"}, "variables": []}}}, "aliases": {".class": "SymbolTableNode", "implicit": true, "kind": "Mdef", "node": {".class": "Var", "flags": [], "fullname": "maggma.stores.advanced_stores.AliasingStore.aliases", "name": "aliases", "type": {".class": "Instance", "args": [{".class": "AnyType", "missing_import_name": null, "source_any": null, "type_of_any": 4}, {".class": "AnyType", "missing_import_name": null, "source_any": null, "type_of_any": 4}], "type_ref": "builtins.dict"}}}, "close": {".class": "SymbolTableNode", "kind": "Mdef", "node": {".class": "FuncDef", "arg_kinds": [0], "arg_names": ["self"], "flags": [], "fullname": "maggma.stores.advanced_stores.AliasingStore.close", "name": "close", "type": null}}, "collection": {".class": "SymbolTableNode", "kind": "Mdef", "node": {".class": "Decorator", "func": {".class": "FuncDef", "arg_kinds": [0], "arg_names": ["self"], "flags": ["is_property", "is_decorated"], "fullname": "maggma.stores.advanced_stores.AliasingStore.collection", "name": "collection", "type": null}, "is_overload": false, "var": {".class": "Var", "flags": ["is_initialized_in_class", "is_property", "is_ready"], "fullname": null, "name": "collection", "type": {".class": "CallableType", "arg_kinds": [0], "arg_names": ["self"], "arg_types": ["maggma.stores.advanced_stores.AliasingStore"], "bound_args": [], "def_extras": {}, "fallback": "builtins.function", "implicit": true, "is_ellipsis_args": false, "name": "collection of AliasingStore", "ret_type": {".class": "AnyType", "missing_import_name": null, "source_any": null, "type_of_any": 1}, "variables": []}}}}, "connect": {".class": "SymbolTableNode", "kind": "Mdef", "node": {".class": "FuncDef", "arg_kinds": [0, 1], "arg_names": ["self", "force_reset"], "flags": [], "fullname": "maggma.stores.advanced_stores.AliasingStore.connect", "name": "connect", "type": null}}, "count": {".class": "SymbolTableNode", "kind": "Mdef", "node": {".class": "FuncDef", "arg_kinds": [0, 1], "arg_names": ["self", "criteria"], "flags": [], "fullname": "maggma.stores.advanced_stores.AliasingStore.count", "name": "count", "type": {".class": "CallableType", "arg_kinds": [0, 1], "arg_names": ["self", "criteria"], "arg_types": ["maggma.stores.advanced_stores.AliasingStore", {".class": "UnionType", "items": [{".class": "Instance", "args": [{".class": "AnyType", "missing_import_name": null, "source_any": null, "type_of_any": 4}, {".class": "AnyType", "missing_import_name": null, "source_any": null, "type_of_any": 4}], "type_ref": "builtins.dict"}, {".class": "NoneType"}]}], "bound_args": [], "def_extras": {"first_arg": "self"}, "fallback": "builtins.function", "implicit": false, "is_ellipsis_args": false, "name": "count of AliasingStore", "ret_type": "builtins.int", "variables": []}}}, "distinct": {".class": "SymbolTableNode", "kind": "Mdef", "node": {".class": "FuncDef", "arg_kinds": [0, 0, 1, 1], "arg_names": ["self", "field", "criteria", "all_exist"], "flags": [], "fullname": "maggma.stores.advanced_stores.AliasingStore.distinct", "name": "distinct", "type": {".class": "CallableType", "arg_kinds": [0, 0, 1, 1], "arg_names": ["self", "field", "criteria", "all_exist"], "arg_types": ["maggma.stores.advanced_stores.AliasingStore", "builtins.str", {".class": "UnionType", "items": [{".class": "Instance", "args": [{".class": "AnyType", "missing_import_name": null, "source_any": null, "type_of_any": 4}, {".class": "AnyType", "missing_import_name": null, "source_any": null, "type_of_any": 4}], "type_ref": "builtins.dict"}, {".class": "NoneType"}]}, "builtins.bool"], "bound_args": [], "def_extras": {"first_arg": "self"}, "fallback": "builtins.function", "implicit": false, "is_ellipsis_args": false, "name": "distinct of AliasingStore", "ret_type": {".class": "Instance", "args": [{".class": "AnyType", "missing_import_name": null, "source_any": null, "type_of_any": 4}], "type_ref": "builtins.list"}, "variables": []}}}, "ensure_index": {".class": "SymbolTableNode", "kind": "Mdef", "node": {".class": "FuncDef", "arg_kinds": [0, 0, 1, 4], "arg_names": ["self", "key", "unique", "kwargs"], "flags": [], "fullname": "maggma.stores.advanced_stores.AliasingStore.ensure_index", "name": "ensure_index", "type": null}}, "groupby": {".class": "SymbolTableNode", "kind": "Mdef", "node": {".class": "FuncDef", "arg_kinds": [0, 0, 1, 1, 1, 1, 1], "arg_names": ["self", "keys", "criteria", "properties", "sort", "skip", "limit"], "flags": [], "fullname": "maggma.stores.advanced_stores.AliasingStore.groupby", "name": "groupby", "type": {".class": "CallableType", "arg_kinds": [0, 0, 1, 1, 1, 1, 1], "arg_names": ["self", "keys", "criteria", "properties", "sort", "skip", "limit"], "arg_types": ["maggma.stores.advanced_stores.AliasingStore", {".class": "UnionType", "items": [{".class": "Instance", "args": ["builtins.str"], "type_ref": "builtins.list"}, "builtins.str"]}, {".class": "UnionType", "items": [{".class": "Instance", "args": [{".class": "AnyType", "missing_import_name": null, "source_any": null, "type_of_any": 4}, {".class": "AnyType", "missing_import_name": null, "source_any": null, "type_of_any": 4}], "type_ref": "builtins.dict"}, {".class": "NoneType"}]}, {".class": "UnionType", "items": [{".class": "Instance", "args": [{".class": "AnyType", "missing_import_name": null, "source_any": null, "type_of_any": 4}, {".class": "AnyType", "missing_import_name": null, "source_any": null, "type_of_any": 4}], "type_ref": "builtins.dict"}, {".class": "Instance", "args": [{".class": "AnyType", "missing_import_name": null, "source_any": null, "type_of_any": 4}], "type_ref": "builtins.list"}, {".class": "NoneType"}]}, {".class": "UnionType", "items": [{".class": "Instance", "args": ["builtins.str", "maggma.core.store.Sort"], "type_ref": "builtins.dict"}, {".class": "NoneType"}]}, "builtins.int", "builtins.int"], "bound_args": [], "def_extras": {"first_arg": "self"}, "fallback": "builtins.function", "implicit": false, "is_ellipsis_args": false, "name": "groupby of AliasingStore", "ret_type": {".class": "Instance", "args": [{".class": "TupleType", "implicit": false, "items": [{".class": "Instance", "args": [{".class": "AnyType", "missing_import_name": null, "source_any": null, "type_of_any": 4}, {".class": "AnyType", "missing_import_name": null, "source_any": null, "type_of_any": 4}], "type_ref": "builtins.dict"}, {".class": "Instance", "args": [{".class": "Instance", "args": [{".class": "AnyType", "missing_import_name": null, "source_any": null, "type_of_any": 4}, {".class": "AnyType", "missing_import_name": null, "source_any": null, "type_of_any": 4}], "type_ref": "builtins.dict"}], "type_ref": "builtins.list"}], "partial_fallback": {".class": "Instance", "args": [{".class": "AnyType", "missing_import_name": null, "source_any": null, "type_of_any": 6}], "type_ref": "builtins.tuple"}}], "type_ref": "typing.Iterator"}, "variables": []}}}, "kwargs": {".class": "SymbolTableNode", "implicit": true, "kind": "Mdef", "node": {".class": "Var", "flags": [], "fullname": "maggma.stores.advanced_stores.AliasingStore.kwargs", "name": "kwargs", "type": {".class": "Instance", "args": ["builtins.str", {".class": "AnyType", "missing_import_name": null, "source_any": null, "type_of_any": 1}], "type_ref": "builtins.dict"}}}, "name": {".class": "SymbolTableNode", "kind": "Mdef", "node": {".class": "FuncDef", "arg_kinds": [0], "arg_names": ["self"], "flags": [], "fullname": "maggma.stores.advanced_stores.AliasingStore.name", "name": "name", "type": {".class": "CallableType", "arg_kinds": [0], "arg_names": ["self"], "arg_types": ["maggma.stores.advanced_stores.AliasingStore"], "bound_args": [], "def_extras": {"first_arg": "self"}, "fallback": "builtins.function", "implicit": false, "is_ellipsis_args": false, "name": "name of AliasingStore", "ret_type": "builtins.str", "variables": []}}}, "query": {".class": "SymbolTableNode", "kind": "Mdef", "node": {".class": "FuncDef", "arg_kinds": [0, 1, 1, 1, 1, 1], "arg_names": ["self", "criteria", "properties", "sort", "skip", "limit"], "flags": ["is_generator"], "fullname": "maggma.stores.advanced_stores.AliasingStore.query", "name": "query", "type": {".class": "CallableType", "arg_kinds": [0, 1, 1, 1, 1, 1], "arg_names": ["self", "criteria", "properties", "sort", "skip", "limit"], "arg_types": ["maggma.stores.advanced_stores.AliasingStore", {".class": "UnionType", "items": [{".class": "Instance", "args": [{".class": "AnyType", "missing_import_name": null, "source_any": null, "type_of_any": 4}, {".class": "AnyType", "missing_import_name": null, "source_any": null, "type_of_any": 4}], "type_ref": "builtins.dict"}, {".class": "NoneType"}]}, {".class": "UnionType", "items": [{".class": "Instance", "args": [{".class": "AnyType", "missing_import_name": null, "source_any": null, "type_of_any": 4}, {".class": "AnyType", "missing_import_name": null, "source_any": null, "type_of_any": 4}], "type_ref": "builtins.dict"}, {".class": "Instance", "args": [{".class": "AnyType", "missing_import_name": null, "source_any": null, "type_of_any": 4}], "type_ref": "builtins.list"}, {".class": "NoneType"}]}, {".class": "UnionType", "items": [{".class": "Instance", "args": ["builtins.str", "maggma.core.store.Sort"], "type_ref": "builtins.dict"}, {".class": "NoneType"}]}, "builtins.int", "builtins.int"], "bound_args": [], "def_extras": {"first_arg": "self"}, "fallback": "builtins.function", "implicit": false, "is_ellipsis_args": false, "name": "query of AliasingStore", "ret_type": {".class": "Instance", "args": [{".class": "Instance", "args": [{".class": "AnyType", "missing_import_name": null, "source_any": null, "type_of_any": 4}, {".class": "AnyType", "missing_import_name": null, "source_any": null, "type_of_any": 4}], "type_ref": "builtins.dict"}], "type_ref": "typing.Iterator"}, "variables": []}}}, "remove_docs": {".class": "SymbolTableNode", "kind": "Mdef", "node": {".class": "FuncDef", "arg_kinds": [0, 0], "arg_names": ["self", "criteria"], "flags": [], "fullname": "maggma.stores.advanced_stores.AliasingStore.remove_docs", "name": "remove_docs", "type": {".class": "CallableType", "arg_kinds": [0, 0], "arg_names": ["self", "criteria"], "arg_types": ["maggma.stores.advanced_stores.AliasingStore", {".class": "Instance", "args": [{".class": "AnyType", "missing_import_name": null, "source_any": null, "type_of_any": 4}, {".class": "AnyType", "missing_import_name": null, "source_any": null, "type_of_any": 4}], "type_ref": "builtins.dict"}], "bound_args": [], "def_extras": {"first_arg": "self"}, "fallback": "builtins.function", "implicit": false, "is_ellipsis_args": false, "name": "remove_docs of AliasingStore", "ret_type": {".class": "AnyType", "missing_import_name": null, "source_any": null, "type_of_any": 1}, "variables": []}}}, "reverse_aliases": {".class": "SymbolTableNode", "implicit": true, "kind": "Mdef", "node": {".class": "Var", "flags": [], "fullname": "maggma.stores.advanced_stores.AliasingStore.reverse_aliases", "name": "reverse_aliases", "type": {".class": "Instance", "args": [{".class": "AnyType", "missing_import_name": null, "source_any": {".class": "AnyType", "missing_import_name": null, "source_any": null, "type_of_any": 4}, "type_of_any": 7}, {".class": "AnyType", "missing_import_name": null, "source_any": {".class": "AnyType", "missing_import_name": null, "source_any": null, "type_of_any": 4}, "type_of_any": 7}], "type_ref": "builtins.dict"}}}, "store": {".class": "SymbolTableNode", "implicit": true, "kind": "Mdef", "node": {".class": "Var", "flags": [], "fullname": "maggma.stores.advanced_stores.AliasingStore.store", "name": "store", "type": "maggma.core.store.Store"}}, "update": {".class": "SymbolTableNode", "kind": "Mdef", "node": {".class": "FuncDef", "arg_kinds": [0, 0, 1], "arg_names": ["self", "docs", "key"], "flags": [], "fullname": "maggma.stores.advanced_stores.AliasingStore.update", "name": "update", "type": {".class": "CallableType", "arg_kinds": [0, 0, 1], "arg_names": ["self", "docs", "key"], "arg_types": ["maggma.stores.advanced_stores.AliasingStore", {".class": "UnionType", "items": [{".class": "Instance", "args": [{".class": "Instance", "args": [{".class": "AnyType", "missing_import_name": null, "source_any": null, "type_of_any": 4}, {".class": "AnyType", "missing_import_name": null, "source_any": null, "type_of_any": 4}], "type_ref": "builtins.dict"}], "type_ref": "builtins.list"}, {".class": "Instance", "args": [{".class": "AnyType", "missing_import_name": null, "source_any": null, "type_of_any": 4}, {".class": "AnyType", "missing_import_name": null, "source_any": null, "type_of_any": 4}], "type_ref": "builtins.dict"}]}, {".class": "UnionType", "items": [{".class": "Instance", "args": [{".class": "AnyType", "missing_import_name": null, "source_any": null, "type_of_any": 4}], "type_ref": "builtins.list"}, "builtins.str", {".class": "NoneType"}]}], "bound_args": [], "def_extras": {"first_arg": "self"}, "fallback": "builtins.function", "implicit": false, "is_ellipsis_args": false, "name": "update of AliasingStore", "ret_type": {".class": "AnyType", "missing_import_name": null, "source_any": null, "type_of_any": 1}, "variables": []}}}}, "tuple_type": null, "type_vars": [], "typeddict_type": null}}, "Client": {".class": "SymbolTableNode", "kind": "Gdef", "node": {".class": "Var", "flags": ["is_suppressed_import", "is_ready"], "fullname": "maggma.stores.advanced_stores.Client", "name": "Client", "type": {".class": "AnyType", "missing_import_name": "maggma.stores.advanced_stores.Client", "source_any": null, "type_of_any": 3}}}, "Config": {".class": "SymbolTableNode", "kind": "Gdef", "node": {".class": "Var", "flags": ["is_suppressed_import", "is_ready"], "fullname": "maggma.stores.advanced_stores.Config", "name": "Config", "type": {".class": "AnyType", "missing_import_name": "maggma.stores.advanced_stores.Config", "source_any": null, "type_of_any": 3}}}, "Dict": {".class": "SymbolTableNode", "cross_ref": "typing.Dict", "kind": "Gdef"}, "Iterator": {".class": "SymbolTableNode", "cross_ref": "typing.Iterator", "kind": "Gdef"}, "List": {".class": "SymbolTableNode", "cross_ref": "typing.List", "kind": "Gdef"}, "MongoStore": {".class": "SymbolTableNode", "cross_ref": "maggma.stores.mongolike.MongoStore", "kind": "Gdef"}, "MongograntStore": {".class": "SymbolTableNode", "kind": "Gdef", "node": {".class": "TypeInfo", "_promote": null, "abstract_attributes": [], "bases": ["maggma.stores.mongolike.MongoStore"], "declared_metaclass": null, "defn": {".class": "ClassDef", "fullname": "maggma.stores.advanced_stores.MongograntStore", "name": "MongograntStore", "type_vars": []}, "flags": ["fallback_to_any"], "fullname": "maggma.stores.advanced_stores.MongograntStore", "metaclass_type": "abc.ABCMeta", "metadata": {}, "module_name": "maggma.stores.advanced_stores", "mro": ["maggma.stores.advanced_stores.MongograntStore", "maggma.stores.mongolike.MongoStore", "maggma.core.store.Store", "builtins.object"], "names": {".class": "SymbolTable", "__eq__": {".class": "SymbolTableNode", "kind": "Mdef", "node": {".class": "FuncDef", "arg_kinds": [0, 0], "arg_names": ["self", "other"], "flags": [], "fullname": "maggma.stores.advanced_stores.MongograntStore.__eq__", "name": "__eq__", "type": {".class": "CallableType", "arg_kinds": [0, 0], "arg_names": [null, null], "arg_types": ["maggma.stores.advanced_stores.MongograntStore", "builtins.object"], "bound_args": [], "def_extras": {"first_arg": "self"}, "fallback": "builtins.function", "implicit": false, "is_ellipsis_args": false, "name": "__eq__ of MongograntStore", "ret_type": "builtins.bool", "variables": []}}}, "__hash__": {".class": "SymbolTableNode", "kind": "Mdef", "node": {".class": "FuncDef", "arg_kinds": [0], "arg_names": ["self"], "flags": [], "fullname": "maggma.stores.advanced_stores.MongograntStore.__hash__", "name": "__hash__", "type": null}}, "__init__": {".class": "SymbolTableNode", "kind": "Mdef", "node": {".class": "FuncDef", "arg_kinds": [0, 0, 0, 1, 4], "arg_names": ["self", "mongogrant_spec", "collection_name", "mgclient_config_path", "kwargs"], "flags": [], "fullname": "maggma.stores.advanced_stores.MongograntStore.__init__", "name": "__init__", "type": {".class": "CallableType", "arg_kinds": [0, 0, 0, 1, 4], "arg_names": ["self", "mongogrant_spec", "collection_name", "mgclient_config_path", "kwargs"], "arg_types": ["maggma.stores.advanced_stores.MongograntStore", "builtins.str", "builtins.str", {".class": "UnionType", "items": ["builtins.str", {".class": "NoneType"}]}, {".class": "AnyType", "missing_import_name": null, "source_any": null, "type_of_any": 1}], "bound_args": [], "def_extras": {"first_arg": "self"}, "fallback": "builtins.function", "implicit": false, "is_ellipsis_args": false, "name": "__init__ of MongograntStore", "ret_type": {".class": "NoneType"}, "variables": []}}}, "from_collection": {".class": "SymbolTableNode", "kind": "Mdef", "node": {".class": "Decorator", "func": {".class": "FuncDef", "arg_kinds": [0, 0], "arg_names": ["cls", "collection"], "flags": ["is_class", "is_decorated"], "fullname": "maggma.stores.advanced_stores.MongograntStore.from_collection", "name": "from_collection", "type": null}, "is_overload": false, "var": {".class": "Var", "flags": ["is_initialized_in_class", "is_classmethod", "is_ready"], "fullname": null, "name": "from_collection", "type": {".class": "CallableType", "arg_kinds": [0, 0], "arg_names": ["cls", "collection"], "arg_types": [{".class": "TypeType", "item": "maggma.stores.advanced_stores.MongograntStore"}, {".class": "AnyType", "missing_import_name": null, "source_any": null, "type_of_any": 1}], "bound_args": [], "def_extras": {}, "fallback": "builtins.function", "implicit": true, "is_ellipsis_args": false, "name": "from_collection of MongograntStore", "ret_type": {".class": "AnyType", "missing_import_name": null, "source_any": null, "type_of_any": 1}, "variables": []}}}}, "from_db_file": {".class": "SymbolTableNode", "kind": "Mdef", "node": {".class": "Decorator", "func": {".class": "FuncDef", "arg_kinds": [0, 0], "arg_names": ["cls", "file"], "flags": ["is_class", "is_decorated"], "fullname": "maggma.stores.advanced_stores.MongograntStore.from_db_file", "name": "from_db_file", "type": null}, "is_overload": false, "var": {".class": "Var", "flags": ["is_initialized_in_class", "is_classmethod", "is_ready"], "fullname": null, "name": "from_db_file", "type": {".class": "CallableType", "arg_kinds": [0, 0], "arg_names": ["cls", "file"], "arg_types": [{".class": "TypeType", "item": "maggma.stores.advanced_stores.MongograntStore"}, {".class": "AnyType", "missing_import_name": null, "source_any": null, "type_of_any": 1}], "bound_args": [], "def_extras": {}, "fallback": "builtins.function", "implicit": true, "is_ellipsis_args": false, "name": "from_db_file of MongograntStore", "ret_type": {".class": "AnyType", "missing_import_name": null, "source_any": null, "type_of_any": 1}, "variables": []}}}}, "mgclient_config_path": {".class": "SymbolTableNode", "implicit": true, "kind": "Mdef", "node": {".class": "Var", "flags": [], "fullname": "maggma.stores.advanced_stores.MongograntStore.mgclient_config_path", "name": "mgclient_config_path", "type": {".class": "UnionType", "items": ["builtins.str", {".class": "NoneType"}]}}}, "mongogrant_spec": {".class": "SymbolTableNode", "implicit": true, "kind": "Mdef", "node": {".class": "Var", "flags": [], "fullname": "maggma.stores.advanced_stores.MongograntStore.mongogrant_spec", "name": "mongogrant_spec", "type": "builtins.str"}}, "name": {".class": "SymbolTableNode", "kind": "Mdef", "node": {".class": "Decorator", "func": {".class": "FuncDef", "arg_kinds": [0], "arg_names": ["self"], "flags": ["is_property", "is_decorated"], "fullname": "maggma.stores.advanced_stores.MongograntStore.name", "name": "name", "type": null}, "is_overload": false, "var": {".class": "Var", "flags": ["is_initialized_in_class", "is_property", "is_ready"], "fullname": null, "name": "name", "type": {".class": "CallableType", "arg_kinds": [0], "arg_names": ["self"], "arg_types": ["maggma.stores.advanced_stores.MongograntStore"], "bound_args": [], "def_extras": {}, "fallback": "builtins.function", "implicit": true, "is_ellipsis_args": false, "name": "name of MongograntStore", "ret_type": {".class": "AnyType", "missing_import_name": null, "source_any": null, "type_of_any": 1}, "variables": []}}}}}, "tuple_type": null, "type_vars": [], "typeddict_type": null}}, "Optional": {".class": "SymbolTableNode", "cross_ref": "typing.Optional", "kind": "Gdef"}, "SandboxStore": {".class": "SymbolTableNode", "kind": "Gdef", "node": {".class": "TypeInfo", "_promote": null, "abstract_attributes": [], "bases": ["maggma.core.store.Store"], "declared_metaclass": null, "defn": {".class": "ClassDef", "fullname": "maggma.stores.advanced_stores.SandboxStore", "name": "SandboxStore", "type_vars": []}, "flags": ["fallback_to_any"], "fullname": "maggma.stores.advanced_stores.SandboxStore", "metaclass_type": "abc.ABCMeta", "metadata": {}, "module_name": "maggma.stores.advanced_stores", "mro": ["maggma.stores.advanced_stores.SandboxStore", "maggma.core.store.Store", "builtins.object"], "names": {".class": "SymbolTable", "__eq__": {".class": "SymbolTableNode", "kind": "Mdef", "node": {".class": "FuncDef", "arg_kinds": [0, 0], "arg_names": ["self", "other"], "flags": [], "fullname": "maggma.stores.advanced_stores.SandboxStore.__eq__", "name": "__eq__", "type": {".class": "CallableType", "arg_kinds": [0, 0], "arg_names": [null, null], "arg_types": ["maggma.stores.advanced_stores.SandboxStore", "builtins.object"], "bound_args": [], "def_extras": {"first_arg": "self"}, "fallback": "builtins.function", "implicit": false, "is_ellipsis_args": false, "name": "__eq__ of SandboxStore", "ret_type": "builtins.bool", "variables": []}}}, "__init__": {".class": "SymbolTableNode", "kind": "Mdef", "node": {".class": "FuncDef", "arg_kinds": [0, 0, 0, 1], "arg_names": ["self", "store", "sandbox", "exclusive"], "flags": [], "fullname": "maggma.stores.advanced_stores.SandboxStore.__init__", "name": "__init__", "type": {".class": "CallableType", "arg_kinds": [0, 0, 0, 1], "arg_names": ["self", "store", "sandbox", "exclusive"], "arg_types": ["maggma.stores.advanced_stores.SandboxStore", "maggma.core.store.Store", "builtins.str", "builtins.bool"], "bound_args": [], "def_extras": {"first_arg": "self"}, "fallback": "builtins.function", "implicit": false, "is_ellipsis_args": false, "name": "__init__ of SandboxStore", "ret_type": {".class": "NoneType"}, "variables": []}}}, "close": {".class": "SymbolTableNode", "kind": "Mdef", "node": {".class": "FuncDef", "arg_kinds": [0], "arg_names": ["self"], "flags": [], "fullname": "maggma.stores.advanced_stores.SandboxStore.close", "name": "close", "type": null}}, "collection": {".class": "SymbolTableNode", "kind": "Mdef", "node": {".class": "Decorator", "func": {".class": "FuncDef", "arg_kinds": [0], "arg_names": ["self"], "flags": ["is_property", "is_decorated"], "fullname": "maggma.stores.advanced_stores.SandboxStore.collection", "name": "collection", "type": null}, "is_overload": false, "var": {".class": "Var", "flags": ["is_initialized_in_class", "is_property", "is_ready"], "fullname": null, "name": "collection", "type": {".class": "CallableType", "arg_kinds": [0], "arg_names": ["self"], "arg_types": ["maggma.stores.advanced_stores.SandboxStore"], "bound_args": [], "def_extras": {}, "fallback": "builtins.function", "implicit": true, "is_ellipsis_args": false, "name": "collection of SandboxStore", "ret_type": {".class": "AnyType", "missing_import_name": null, "source_any": null, "type_of_any": 1}, "variables": []}}}}, "connect": {".class": "SymbolTableNode", "kind": "Mdef", "node": {".class": "FuncDef", "arg_kinds": [0, 1], "arg_names": ["self", "force_reset"], "flags": [], "fullname": "maggma.stores.advanced_stores.SandboxStore.connect", "name": "connect", "type": null}}, "count": {".class": "SymbolTableNode", "kind": "Mdef", "node": {".class": "FuncDef", "arg_kinds": [0, 1], "arg_names": ["self", "criteria"], "flags": [], "fullname": "maggma.stores.advanced_stores.SandboxStore.count", "name": "count", "type": {".class": "CallableType", "arg_kinds": [0, 1], "arg_names": ["self", "criteria"], "arg_types": ["maggma.stores.advanced_stores.SandboxStore", {".class": "UnionType", "items": [{".class": "Instance", "args": [{".class": "AnyType", "missing_import_name": null, "source_any": null, "type_of_any": 4}, {".class": "AnyType", "missing_import_name": null, "source_any": null, "type_of_any": 4}], "type_ref": "builtins.dict"}, {".class": "NoneType"}]}], "bound_args": [], "def_extras": {"first_arg": "self"}, "fallback": "builtins.function", "implicit": false, "is_ellipsis_args": false, "name": "count of SandboxStore", "ret_type": "builtins.int", "variables": []}}}, "ensure_index": {".class": "SymbolTableNode", "kind": "Mdef", "node": {".class": "FuncDef", "arg_kinds": [0, 0, 1, 4], "arg_names": ["self", "key", "unique", "kwargs"], "flags": [], "fullname": "maggma.stores.advanced_stores.SandboxStore.ensure_index", "name": "ensure_index", "type": null}}, "exclusive": {".class": "SymbolTableNode", "implicit": true, "kind": "Mdef", "node": {".class": "Var", "flags": [], "fullname": "maggma.stores.advanced_stores.SandboxStore.exclusive", "name": "exclusive", "type": "builtins.bool"}}, "groupby": {".class": "SymbolTableNode", "kind": "Mdef", "node": {".class": "FuncDef", "arg_kinds": [0, 0, 1, 1, 1, 1, 1], "arg_names": ["self", "keys", "criteria", "properties", "sort", "skip", "limit"], "flags": [], "fullname": "maggma.stores.advanced_stores.SandboxStore.groupby", "name": "groupby", "type": {".class": "CallableType", "arg_kinds": [0, 0, 1, 1, 1, 1, 1], "arg_names": ["self", "keys", "criteria", "properties", "sort", "skip", "limit"], "arg_types": ["maggma.stores.advanced_stores.SandboxStore", {".class": "UnionType", "items": [{".class": "Instance", "args": ["builtins.str"], "type_ref": "builtins.list"}, "builtins.str"]}, {".class": "UnionType", "items": [{".class": "Instance", "args": [{".class": "AnyType", "missing_import_name": null, "source_any": null, "type_of_any": 4}, {".class": "AnyType", "missing_import_name": null, "source_any": null, "type_of_any": 4}], "type_ref": "builtins.dict"}, {".class": "NoneType"}]}, {".class": "UnionType", "items": [{".class": "Instance", "args": [{".class": "AnyType", "missing_import_name": null, "source_any": null, "type_of_any": 4}, {".class": "AnyType", "missing_import_name": null, "source_any": null, "type_of_any": 4}], "type_ref": "builtins.dict"}, {".class": "Instance", "args": [{".class": "AnyType", "missing_import_name": null, "source_any": null, "type_of_any": 4}], "type_ref": "builtins.list"}, {".class": "NoneType"}]}, {".class": "UnionType", "items": [{".class": "Instance", "args": ["builtins.str", "maggma.core.store.Sort"], "type_ref": "builtins.dict"}, {".class": "NoneType"}]}, "builtins.int", "builtins.int"], "bound_args": [], "def_extras": {"first_arg": "self"}, "fallback": "builtins.function", "implicit": false, "is_ellipsis_args": false, "name": "groupby of SandboxStore", "ret_type": {".class": "Instance", "args": [{".class": "TupleType", "implicit": false, "items": [{".class": "Instance", "args": [{".class": "AnyType", "missing_import_name": null, "source_any": null, "type_of_any": 4}, {".class": "AnyType", "missing_import_name": null, "source_any": null, "type_of_any": 4}], "type_ref": "builtins.dict"}, {".class": "Instance", "args": [{".class": "Instance", "args": [{".class": "AnyType", "missing_import_name": null, "source_any": null, "type_of_any": 4}, {".class": "AnyType", "missing_import_name": null, "source_any": null, "type_of_any": 4}], "type_ref": "builtins.dict"}], "type_ref": "builtins.list"}], "partial_fallback": {".class": "Instance", "args": [{".class": "AnyType", "missing_import_name": null, "source_any": null, "type_of_any": 6}], "type_ref": "builtins.tuple"}}], "type_ref": "typing.Iterator"}, "variables": []}}}, "name": {".class": "SymbolTableNode", "kind": "Mdef", "node": {".class": "FuncDef", "arg_kinds": [0], "arg_names": ["self"], "flags": [], "fullname": "maggma.stores.advanced_stores.SandboxStore.name", "name": "name", "type": {".class": "CallableType", "arg_kinds": [0], "arg_names": ["self"], "arg_types": ["maggma.stores.advanced_stores.SandboxStore"], "bound_args": [], "def_extras": {"first_arg": "self"}, "fallback": "builtins.function", "implicit": false, "is_ellipsis_args": false, "name": "name of SandboxStore", "ret_type": "builtins.str", "variables": []}}}, "query": {".class": "SymbolTableNode", "kind": "Mdef", "node": {".class": "FuncDef", "arg_kinds": [0, 1, 1, 1, 1, 1], "arg_names": ["self", "criteria", "properties", "sort", "skip", "limit"], "flags": [], "fullname": "maggma.stores.advanced_stores.SandboxStore.query", "name": "query", "type": {".class": "CallableType", "arg_kinds": [0, 1, 1, 1, 1, 1], "arg_names": ["self", "criteria", "properties", "sort", "skip", "limit"], "arg_types": ["maggma.stores.advanced_stores.SandboxStore", {".class": "UnionType", "items": [{".class": "Instance", "args": [{".class": "AnyType", "missing_import_name": null, "source_any": null, "type_of_any": 4}, {".class": "AnyType", "missing_import_name": null, "source_any": null, "type_of_any": 4}], "type_ref": "builtins.dict"}, {".class": "NoneType"}]}, {".class": "UnionType", "items": [{".class": "Instance", "args": [{".class": "AnyType", "missing_import_name": null, "source_any": null, "type_of_any": 4}, {".class": "AnyType", "missing_import_name": null, "source_any": null, "type_of_any": 4}], "type_ref": "builtins.dict"}, {".class": "Instance", "args": [{".class": "AnyType", "missing_import_name": null, "source_any": null, "type_of_any": 4}], "type_ref": "builtins.list"}, {".class": "NoneType"}]}, {".class": "UnionType", "items": [{".class": "Instance", "args": ["builtins.str", "maggma.core.store.Sort"], "type_ref": "builtins.dict"}, {".class": "NoneType"}]}, "builtins.int", "builtins.int"], "bound_args": [], "def_extras": {"first_arg": "self"}, "fallback": "builtins.function", "implicit": false, "is_ellipsis_args": false, "name": "query of SandboxStore", "ret_type": {".class": "Instance", "args": [{".class": "Instance", "args": [{".class": "AnyType", "missing_import_name": null, "source_any": null, "type_of_any": 4}, {".class": "AnyType", "missing_import_name": null, "source_any": null, "type_of_any": 4}], "type_ref": "builtins.dict"}], "type_ref": "typing.Iterator"}, "variables": []}}}, "remove_docs": {".class": "SymbolTableNode", "kind": "Mdef", "node": {".class": "FuncDef", "arg_kinds": [0, 0], "arg_names": ["self", "criteria"], "flags": [], "fullname": "maggma.stores.advanced_stores.SandboxStore.remove_docs", "name": "remove_docs", "type": {".class": "CallableType", "arg_kinds": [0, 0], "arg_names": ["self", "criteria"], "arg_types": ["maggma.stores.advanced_stores.SandboxStore", {".class": "Instance", "args": [{".class": "AnyType", "missing_import_name": null, "source_any": null, "type_of_any": 4}, {".class": "AnyType", "missing_import_name": null, "source_any": null, "type_of_any": 4}], "type_ref": "builtins.dict"}], "bound_args": [], "def_extras": {"first_arg": "self"}, "fallback": "builtins.function", "implicit": false, "is_ellipsis_args": false, "name": "remove_docs of SandboxStore", "ret_type": {".class": "AnyType", "missing_import_name": null, "source_any": null, "type_of_any": 1}, "variables": []}}}, "sandbox": {".class": "SymbolTableNode", "implicit": true, "kind": "Mdef", "node": {".class": "Var", "flags": [], "fullname": "maggma.stores.advanced_stores.SandboxStore.sandbox", "name": "sandbox", "type": "builtins.str"}}, "sbx_criteria": {".class": "SymbolTableNode", "kind": "Mdef", "node": {".class": "Decorator", "func": {".class": "FuncDef", "arg_kinds": [0], "arg_names": ["self"], "flags": ["is_property", "is_decorated"], "fullname": "maggma.stores.advanced_stores.SandboxStore.sbx_criteria", "name": "sbx_criteria", "type": {".class": "CallableType", "arg_kinds": [0], "arg_names": ["self"], "arg_types": ["maggma.stores.advanced_stores.SandboxStore"], "bound_args": [], "def_extras": {"first_arg": "self"}, "fallback": "builtins.function", "implicit": false, "is_ellipsis_args": false, "name": "sbx_criteria of SandboxStore", "ret_type": {".class": "Instance", "args": [{".class": "AnyType", "missing_import_name": null, "source_any": null, "type_of_any": 4}, {".class": "AnyType", "missing_import_name": null, "source_any": null, "type_of_any": 4}], "type_ref": "builtins.dict"}, "variables": []}}, "is_overload": false, "var": {".class": "Var", "flags": ["is_initialized_in_class", "is_property", "is_ready"], "fullname": null, "name": "sbx_criteria", "type": {".class": "CallableType", "arg_kinds": [0], "arg_names": ["self"], "arg_types": ["maggma.stores.advanced_stores.SandboxStore"], "bound_args": [], "def_extras": {"first_arg": "self"}, "fallback": "builtins.function", "implicit": false, "is_ellipsis_args": false, "name": "sbx_criteria of SandboxStore", "ret_type": {".class": "Instance", "args": [{".class": "AnyType", "missing_import_name": null, "source_any": null, "type_of_any": 4}, {".class": "AnyType", "missing_import_name": null, "source_any": null, "type_of_any": 4}], "type_ref": "builtins.dict"}, "variables": []}}}}, "store": {".class": "SymbolTableNode", "implicit": true, "kind": "Mdef", "node": {".class": "Var", "flags": [], "fullname": "maggma.stores.advanced_stores.SandboxStore.store", "name": "store", "type": "maggma.core.store.Store"}}, "update": {".class": "SymbolTableNode", "kind": "Mdef", "node": {".class": "FuncDef", "arg_kinds": [0, 0, 1], "arg_names": ["self", "docs", "key"], "flags": [], "fullname": "maggma.stores.advanced_stores.SandboxStore.update", "name": "update", "type": {".class": "CallableType", "arg_kinds": [0, 0, 1], "arg_names": ["self", "docs", "key"], "arg_types": ["maggma.stores.advanced_stores.SandboxStore", {".class": "UnionType", "items": [{".class": "Instance", "args": [{".class": "Instance", "args": [{".class": "AnyType", "missing_import_name": null, "source_any": null, "type_of_any": 4}, {".class": "AnyType", "missing_import_name": null, "source_any": null, "type_of_any": 4}], "type_ref": "builtins.dict"}], "type_ref": "builtins.list"}, {".class": "Instance", "args": [{".class": "AnyType", "missing_import_name": null, "source_any": null, "type_of_any": 4}, {".class": "AnyType", "missing_import_name": null, "source_any": null, "type_of_any": 4}], "type_ref": "builtins.dict"}]}, {".class": "UnionType", "items": [{".class": "Instance", "args": [{".class": "AnyType", "missing_import_name": null, "source_any": null, "type_of_any": 4}], "type_ref": "builtins.list"}, "builtins.str", {".class": "NoneType"}]}], "bound_args": [], "def_extras": {"first_arg": "self"}, "fallback": "builtins.function", "implicit": false, "is_ellipsis_args": false, "name": "update of SandboxStore", "ret_type": {".class": "AnyType", "missing_import_name": null, "source_any": null, "type_of_any": 1}, "variables": []}}}}, "tuple_type": null, "type_vars": [], "typeddict_type": null}}, "Sort": {".class": "SymbolTableNode", "cross_ref": "maggma.core.store.Sort", "kind": "Gdef"}, "Store": {".class": "SymbolTableNode", "cross_ref": "maggma.core.store.Store", "kind": "Gdef"}, "StoreError": {".class": "SymbolTableNode", "cross_ref": "maggma.core.store.StoreError", "kind": "Gdef"}, "Tuple": {".class": "SymbolTableNode", "cross_ref": "typing.Tuple", "kind": "Gdef"}, "Union": {".class": "SymbolTableNode", "cross_ref": "typing.Union", "kind": "Gdef"}, "VaultStore": {".class": "SymbolTableNode", "kind": "Gdef", "node": {".class": "TypeInfo", "_promote": null, "abstract_attributes": [], "bases": ["maggma.stores.mongolike.MongoStore"], "declared_metaclass": null, "defn": {".class": "ClassDef", "fullname": "maggma.stores.advanced_stores.VaultStore", "name": "VaultStore", "type_vars": []}, "flags": ["fallback_to_any"], "fullname": "maggma.stores.advanced_stores.VaultStore", "metaclass_type": "abc.ABCMeta", "metadata": {}, "module_name": "maggma.stores.advanced_stores", "mro": ["maggma.stores.advanced_stores.VaultStore", "maggma.stores.mongolike.MongoStore", "maggma.core.store.Store", "builtins.object"], "names": {".class": "SymbolTable", "__eq__": {".class": "SymbolTableNode", "kind": "Mdef", "node": {".class": "FuncDef", "arg_kinds": [0, 0], "arg_names": ["self", "other"], "flags": [], "fullname": "maggma.stores.advanced_stores.VaultStore.__eq__", "name": "__eq__", "type": {".class": "CallableType", "arg_kinds": [0, 0], "arg_names": [null, null], "arg_types": ["maggma.stores.advanced_stores.VaultStore", "builtins.object"], "bound_args": [], "def_extras": {"first_arg": "self"}, "fallback": "builtins.function", "implicit": false, "is_ellipsis_args": false, "name": "__eq__ of VaultStore", "ret_type": "builtins.bool", "variables": []}}}, "__init__": {".class": "SymbolTableNode", "kind": "Mdef", "node": {".class": "Decorator", "func": {".class": "FuncDef", "arg_kinds": [0, 0, 0], "arg_names": ["self", "collection_name", "vault_secret_path"], "flags": ["is_decorated"], "fullname": "maggma.stores.advanced_stores.VaultStore.__init__", "name": "__init__", "type": {".class": "CallableType", "arg_kinds": [0, 0, 0], "arg_names": ["self", "collection_name", "vault_secret_path"], "arg_types": ["maggma.stores.advanced_stores.VaultStore", "builtins.str", "builtins.str"], "bound_args": [], "def_extras": {"first_arg": "self"}, "fallback": "builtins.function", "implicit": false, "is_ellipsis_args": false, "name": "__init__ of VaultStore", "ret_type": {".class": "NoneType"}, "variables": []}}, "is_overload": false, "var": {".class": "Var", "flags": ["is_initialized_in_class", "is_ready"], "fullname": null, "name": "__init__", "type": {".class": "AnyType", "missing_import_name": "maggma.stores.advanced_stores.requires", "source_any": {".class": "AnyType", "missing_import_name": "maggma.stores.advanced_stores.requires", "source_any": null, "type_of_any": 3}, "type_of_any": 7}}}}, "vault_secret_path": {".class": "SymbolTableNode", "implicit": true, "kind": "Mdef", "node": {".class": "Var", "flags": [], "fullname": "maggma.stores.advanced_stores.VaultStore.vault_secret_path", "name": "vault_secret_path", "type": "builtins.str"}}}, "tuple_type": null, "type_vars": [], "typeddict_type": null}}, "__doc__": {".class": "SymbolTableNode", "kind": "Gdef", "node": {".class": "Var", "flags": ["is_ready"], "fullname": "maggma.stores.advanced_stores.__doc__", "name": "__doc__", "type": "builtins.str"}}, "__file__": {".class": "SymbolTableNode", "kind": "Gdef", "node": {".class": "Var", "flags": ["is_ready"], "fullname": "maggma.stores.advanced_stores.__file__", "name": "__file__", "type": "builtins.str"}}, "__name__": {".class": "SymbolTableNode", "kind": "Gdef", "node": {".class": "Var", "flags": ["is_ready"], "fullname": "maggma.stores.advanced_stores.__name__", "name": "__name__", "type": "builtins.str"}}, "__package__": {".class": "SymbolTableNode", "kind": "Gdef", "node": {".class": "Var", "flags": ["is_ready"], "fullname": "maggma.stores.advanced_stores.__package__", "name": "__package__", "type": "builtins.str"}}, "check": {".class": "SymbolTableNode", "kind": "Gdef", "node": {".class": "Var", "flags": ["is_suppressed_import", "is_ready"], "fullname": "maggma.stores.advanced_stores.check", "name": "check", "type": {".class": "AnyType", "missing_import_name": "maggma.stores.advanced_stores.check", "source_any": null, "type_of_any": 3}}}, "hvac": {".class": "SymbolTableNode", "kind": "Gdef", "node": {".class": "Var", "flags": ["is_suppressed_import", "is_ready"], "fullname": "maggma.stores.advanced_stores.hvac", "name": "hvac", "type": {".class": "AnyType", "missing_import_name": "maggma.stores.advanced_stores.hvac", "source_any": null, "type_of_any": 3}}}, "json": {".class": "SymbolTableNode", "cross_ref": "json", "kind": "Gdef"}, "lazy_substitute": {".class": "SymbolTableNode", "cross_ref": "maggma.utils.lazy_substitute", "kind": "Gdef"}, "os": {".class": "SymbolTableNode", "cross_ref": "os", "kind": "Gdef"}, "requires": {".class": "SymbolTableNode", "kind": "Gdef", "node": {".class": "Var", "flags": ["is_suppressed_import", "is_ready"], "fullname": "maggma.stores.advanced_stores.requires", "name": "requires", "type": {".class": "AnyType", "missing_import_name": "maggma.stores.advanced_stores.requires", "source_any": null, "type_of_any": 3}}}, "substitute": {".class": "SymbolTableNode", "cross_ref": "maggma.utils.substitute", "kind": "Gdef"}}, "path": "/opt/anaconda3/envs/lbnl/lib/python3.7/site-packages/maggma-0.19.1-py3.7.egg/maggma/stores/advanced_stores.py"}